stashroot/__init__.py
stashroot/client.py
stashroot-0.0.1.dist-info/METADATA
stashroot-0.0.1.dist-info/WHEEL
stashroot-0.0.1.dist-info/top_level.txt
stashroot-0.0.1.dist-info/RECORD
