Metadata-Version: 2.1
Name: stashroot
Version: 0.0.1
Summary: Stashroot Client Library
Author: Kayvan
Requires-Dist: requests
